shucker-0.1.1.dist-info/METADATA
shucker-0.1.1.dist-info/WHEEL
shucker-0.1.1.dist-info/licenses/LICENSE
shucker/__init__.py
shucker/__init__.pyi
shucker/py.typed
shucker/shucker.cpython-311-x86_64-linux-gnu.so
shucker-0.1.1.dist-info/RECORD
