Metadata-Version: 2.4
Name: shucker
Version: 0.1.1
License-File: LICENSE
Summary: Tracking-param filtering library, designed to strip URLs down to their canonical forms
Keywords: adblock,url,tracking
Author: Tom Parker-Shemilt <palfrey@tevp.net>
Author-email: Tom Parker-Shemilt <palfrey@tevp.net>
License: GPL-3.0-only
Project-URL: Source Code, https://github.com/palfrey/shucker
